pyautoconfig/__about__.py
pyautoconfig/__init__.py
pyautoconfig/base_config_loader.py
pyautoconfig/dictionary_config_node.py
pyautoconfig/env_config_loader.py
pyautoconfig/free_config_node.py
pyautoconfig/json_config_loader.py
pyautoconfig/json_config_node.py
pyautoconfig-1.3.0.dist-info/METADATA
pyautoconfig-1.3.0.dist-info/WHEEL
pyautoconfig-1.3.0.dist-info/licenses/LICENSE
pyautoconfig-1.3.0.dist-info/RECORD
