Metadata-Version: 2.3
Name: pyautoconfig
Version: 1.3.0
Summary: Effortlessly describe and load env and Json configurations in Python.
Project-URL: Homepage, https://github.com/Yiannis128/pyautoconfig
Project-URL: Source Code, https://github.com/Yiannis128/pyautoconfig
Project-URL: Issues, https://github.com/Yiannis128/pyautoconfig/issues
Author-email: Yiannis Charalambous <yiannis128@hotmail.com>
License-File: LICENSE
Keywords: config,env,json
Classifier: License :: OSI Approved :: GNU Affero General Public License v3
Classifier: Programming Language :: Python :: 3
Requires-Python: >=3.11
Requires-Dist: python-dotenv
Requires-Dist: typing-extensions
